estimate_mcp_server/__init__.py
estimate_mcp_server/main.py
estimate_mcp_server/tools/__init__.py
estimate_mcp_server/tools/estimate_tools.py
estimate_mcp_server/tools/process_tools.py
estimate_mcp_server/tools/version_tools.py
estimate_mcp_server/utils/__init__.py
estimate_mcp_server/utils/firebase_client.py
estimate_mcp_server-0.1.0.dist-info/METADATA
estimate_mcp_server-0.1.0.dist-info/WHEEL
estimate_mcp_server-0.1.0.dist-info/entry_points.txt
estimate_mcp_server-0.1.0.dist-info/top_level.txt
estimate_mcp_server-0.1.0.dist-info/RECORD
